LICENSE.txt
README.rst
aura/__init__.py
aura/analyzers/__init__.py
aura/analyzers/archive.py
aura/analyzers/base.py
aura/analyzers/data_finder.py
aura/analyzers/detect_redos.py
aura/analyzers/detections.py
aura/analyzers/find_imports.py
aura/analyzers/find_imports_inject.py
aura/analyzers/fs_struct.py
aura/analyzers/package_enrichment.py
aura/analyzers/pypirc.py
aura/analyzers/pyproject.py
aura/analyzers/python/__init__.py
aura/analyzers/python/convert_ast.py
aura/analyzers/python/crypto.py
aura/analyzers/python/jinja.py
aura/analyzers/python/misc.py
aura/analyzers/python/nodes.py
aura/analyzers/python/pattern_matching_visitor.py
aura/analyzers/python/readonly.py
aura/analyzers/python/rewrite_ast.py
aura/analyzers/python/secrets.py
aura/analyzers/python/sqli.py
aura/analyzers/python/taint/__init__.py
aura/analyzers/python/taint/base.py
aura/analyzers/python/taint/visitor.py
aura/analyzers/python/visitor.py
aura/analyzers/python_src_inspector.py
aura/analyzers/requirements_analyzer.py
aura/analyzers/setup.py
aura/analyzers/stats.py
aura/analyzers/typosquatting.py
aura/analyzers/wheel.py
aura/analyzers/xml.py
aura/analyzers/yara_scan.py
aura/apip.py
aura/cache.py
aura/cli.py
aura/commands.py
aura/config.py
aura/data/__init__.py
aura/data/aura_config.yaml
aura/data/rules.yara
aura/data/semantic_rules_schema.json
aura/data/signatures.yaml
aura/diff.py
aura/exceptions.py
aura/github.py
aura/graph.py
aura/info.py
aura/json_proxy.py
aura/main.py
aura/mirror.py
aura/output/__init__.py
aura/output/base.py
aura/output/gitlab.py
aura/output/json.py
aura/output/sarif.py
aura/output/sqlite.py
aura/output/table.py
aura/output/text.py
aura/package.py
aura/package_analyzer.py
aura/pattern_matching.py
aura/plugins.py
aura/prefetch.py
aura/python_executor.py
aura/stack.py
aura/type_definitions.py
aura/typos.py
aura/update.py
aura/uri_handlers/__init__.py
aura/uri_handlers/base.py
aura/uri_handlers/git.py
aura/uri_handlers/local.py
aura/uri_handlers/mirror.py
aura_security-2.1.dist-info/entry_points.txt
aura_security-2.1.dist-info/LICENSE.txt
aura_security-2.1.dist-info/WHEEL
aura_security-2.1.dist-info/METADATA
aura_security-2.1.dist-info/RECORD
