Metadata-Version: 2.1
Name: aura-security
Version: 2.1
Summary: Security auditing and static analysis for python
Home-page: https://aura.sourcecode.ai/
License: GPL-3.0-or-later
Author: Martin Carnogursky
Author-email: admin@sourcecode.ai
Requires-Python: >=3.8,<4.0
Classifier: Development Status :: 3 - Alpha
Classifier: Intended Audience :: Developers
Classifier: Intended Audience :: System Administrators
Classifier: License :: OSI Approved :: GNU General Public License v3 (GPLv3)
Classifier: License :: OSI Approved :: GNU General Public License v3 or later (GPLv3+)
Classifier: Operating System :: POSIX :: Linux
Classifier: Programming Language :: Python :: 3
Classifier: Programming Language :: Python :: 3 :: Only
Classifier: Programming Language :: Python :: 3.10
Classifier: Programming Language :: Python :: 3.8
Classifier: Programming Language :: Python :: 3.9
Classifier: Topic :: Security
Provides-Extra: full
Requires-Dist: GitPython (>=3.1,<3.2); extra == "full"
Requires-Dist: click (>=8.0,<8.1)
Requires-Dist: colorama (>=0.4.4,<0.5.0)
Requires-Dist: defusedxml (>=0.7,<0.8); extra == "full"
Requires-Dist: jinja2 (>=3.0,<3.1)
Requires-Dist: jsonschema (>=3.2,<3.3); extra == "full"
Requires-Dist: networkx (>=2.5,<2.6); extra == "full"
Requires-Dist: packaging (>=20.9,<20.10)
Requires-Dist: prettyprinter (>=0.18.0,<0.19.0)
Requires-Dist: python-magic (>=0.4.24,<0.5.0)
Requires-Dist: python-rapidjson (>=1.0,<1.1); extra == "full"
Requires-Dist: python-tlsh (>=3.17.0,<3.18.0)
Requires-Dist: pytz (>=2021.1,<2021.2)
Requires-Dist: requests (>=2.25.1,<2.26.0)
Requires-Dist: ruamel.yaml (>=0.17.7,<0.18.0)
Requires-Dist: tomlkit (>=0.7,<0.8); extra == "full"
Requires-Dist: tqdm (>=4.61,<4.62)
Requires-Dist: yara-python (>=4.0.5,<4.1.0); extra == "full"
Project-URL: Bug Tracker, https://github.com/SourceCode-AI/aura/issues
Project-URL: Documentation, https://docs.aura.sourcecode.ai/
Project-URL: Repository, https://github.com/SourceCode-AI/aura
